gd_kafka
