Metadata-Version: 2.1
Name: gd-kafka
Version: 0.0.3
Summary: Greendeck Kafka Package
Home-page: https://github.com/pypa/sampleproject
Author: Rishabh Garg
Author-email: rishabh@greendeck.co
License: UNKNOWN
Platform: UNKNOWN
Classifier: Programming Language :: Python :: 3
Classifier: License :: OSI Approved :: MIT License
Classifier: Operating System :: OS Independent
